stdclasses/__init__.py
stdclasses/conceitos.py
stdclasses/enviaremail.py
stdclasses/funcoes.py
stdclasses/spark.py
stdclasses-0.0.73.dist-info/DESCRIPTION.rst
stdclasses-0.0.73.dist-info/METADATA
stdclasses-0.0.73.dist-info/RECORD
stdclasses-0.0.73.dist-info/WHEEL
stdclasses-0.0.73.dist-info/metadata.json
stdclasses-0.0.73.dist-info/top_level.txt
