Metadata-Version: 2.0
Name: stdclasses
Version: 0.0.73
Summary: Classes to help
Home-page: https://github.com/guimartino/stdclasses
Author: Guilherme Martino
Author-email: gui.martino@hotmail.com
License: MIT
Platform: UNKNOWN
Classifier: Development Status :: 4 - Beta
Classifier: Intended Audience :: System Administrators
Classifier: License :: OSI Approved :: Apache Software License
Classifier: Programming Language :: Python :: 3
Requires-Dist: pandas (>=0.23.4)
